MonteCarloPy-0.1.dist-info/METADATA
MonteCarloPy-0.1.dist-info/RECORD
MonteCarloPy-0.1.dist-info/WHEEL
MonteCarloPy-0.1.dist-info/top_level.txt
PyMonteCarlo/__init__.py
PyMonteCarlo/mcs.py
