Metadata-Version: 2.1
Name: MonteCarloPy
Version: 0.1
Summary: PyMonteCarlo is a module that has helper function for monte carlo simulations
Home-page: https://github.com/SonicRoshan/PyMonteCarlo
Author: Roshan J Mehta
Author-email: sonicroshan122@gmail.com
License: UNKNOWN
Platform: UNKNOWN
Classifier: Programming Language :: Python :: 3
Classifier: License :: OSI Approved :: MIT License
Classifier: Operating System :: OS Independent
